LICENSE
README.md
setup.py
plateinputs/__init__.py
plateinputs/model.py
plateinputs.egg-info/PKG-INFO
plateinputs.egg-info/SOURCES.txt
plateinputs.egg-info/dependency_links.txt
plateinputs.egg-info/requires.txt
plateinputs.egg-info/top_level.txt
plateinputs/mesher/__init__.py
plateinputs/mesher/earthsurf.py
plateinputs/mesher/functions.py
plateinputs/tectonics/__init__.py
plateinputs/tectonics/plates.py
plateinputs/tools/__init__.py
plateinputs/tools/inputparser.py
plateinputs/tools/outmesh.py