Metadata-Version: 2.1
Name: plateinputs
Version: 0.0.1
Summary: A Python interface to build paleogeography forcing in goSPL
Home-page: https://github.com/Geodels/plateInputs
Author: Tristan Salles
Author-email: tristan.salles@sydney.edu.au
License: GPLv3
Keywords: python,paleogeography,science
Platform: UNKNOWN
Classifier: Intended Audience :: Science/Research
Classifier: Operating System :: Unix
Classifier: Operating System :: MacOS
Classifier: Programming Language :: Python :: 3.6
Classifier: Programming Language :: Python :: 3.7
Classifier: Programming Language :: Python :: 3.8
Classifier: Programming Language :: Python :: 3.9
Requires-Python: >=3
License-File: LICENSE
